{
    "mixedshag": {
        "blender": "Bayside",
        "name": "Mixed Shag",
        "blendType": "Virginia Based",
        "description": "Originally blended for pipe smokers, the Bayside Tobacco not only represents great value but this medium strength blend burns slowly, allowing you to enjoy your smoke. The resealable pouch is designed to keep the tobacco fresh, from the first smoke to the last.",
        "contents": "Unknown,  Virginia",
        "cut": "Shag",
        "packaging": "50g Pouch",
        "country": "Germany",
        "production": "Currently available",
        "imagePath": "../blend_pictures/Bayside - Mixed Shag.jpg",
        "averageRating": 1.5,
        "reviewCount": 2,
        "ratings": {
            "strength": {
                "level": "Medium",
                "distribution": {
                    "Extremely Mild": 0.0,
                    "Very Mild": 0.0,
                    "Mild": 0.0,
                    "Mild to Medium": 0.0,
                    "Medium": 100.0,
                    "Medium to Strong": 0.0,
                    "Strong": 0.0,
                    "Very Strong": 0.0,
                    "Extremely Strong": 0.0,
                    "Overwhelming": 0.0
                }
            },
            "flavoring": {
                "level": "Extremely Mild",
                "distribution": {
                    "None Detected": 0.0,
                    "Extremely Mild": 100.0,
                    "Very Mild": 100.0,
                    "Mild": 0.0,
                    "Mild to Medium": 0.0,
                    "Medium": 0.0,
                    "Medium to Strong": 0.0,
                    "Strong": 0.0,
                    "Very Strong": 0.0,
                    "Extra Strong": 0.0
                }
            },
            "roomNote": {
                "level": "Unnoticeable",
                "distribution": {
                    "Unnoticeable": 100.0,
                    "Pleasant": 100.0,
                    "Very Pleasant": 0.0,
                    "Pleasant to Tolerable": 0.0,
                    "Tolerable": 0.0,
                    "Tolerable to Strong": 0.0,
                    "Strong": 0.0,
                    "Very Strong": 0.0,
                    "Extra Strong": 0.0,
                    "Overwhelming": 0.0
                }
            },
            "taste": {
                "level": "Mild",
                "distribution": {
                    "Extremely Mild (Flat)": 0.0,
                    "Very Mild": 0.0,
                    "Mild": 100.0,
                    "Mild to Medium": 0.0,
                    "Medium": 100.0,
                    "Medium to Full": 0.0,
                    "Full": 0.0,
                    "Very Full": 0.0,
                    "Extra Full": 0.0,
                    "Overwhelming": 0.0
                }
            }
        }
    }
}