{
    "honeyroast": {
        "blender": "Boswell Pipes & Tobacco",
        "name": "Honey Roast",
        "blendType": "Aromatic",
        "description": "Honey Roast is another Superb blend of Cut Golden Cavendish, Black and Fire-cured Cavendish. Black Honey Cavendish added as enhancer to make an all day smoke.  It\u2019s a delicious honey taste sensation that you will want to experience with your bowl.\nThe name  says it all  - Boswell\u2019s Honey Roast,  J.M. has enhanced the Honey flavor by adding extra Honey flavor to really bring out the taste but still keep it smooth and slow burning.",
        "contents": "Black Cavendish, Cavendish",
        "cut": "Ribbon",
        "packaging": "bulk",
        "country": "United States",
        "production": "Currently available",
        "imagePath": "../blend_pictures/Boswell Pipes & Tobacco - Honey Roast.jpg",
        "averageRating": 3.67,
        "reviewCount": 3,
        "ratings": {
            "strength": {
                "level": "Very Mild",
                "distribution": {
                    "Extremely Mild": 0.0,
                    "Very Mild": 100.0,
                    "Mild": 0.0,
                    "Mild to Medium": 0.0,
                    "Medium": 0.0,
                    "Medium to Strong": 0.0,
                    "Strong": 0.0,
                    "Very Strong": 0.0,
                    "Extremely Strong": 0.0,
                    "Overwhelming": 0.0
                }
            },
            "flavoring": {
                "level": "Medium",
                "distribution": {
                    "None Detected": 0.0,
                    "Extremely Mild": 0.0,
                    "Very Mild": 0.0,
                    "Mild": 0.0,
                    "Mild to Medium": 100.0,
                    "Medium": 100.0,
                    "Medium to Strong": 0.0,
                    "Strong": 100.0,
                    "Very Strong": 0.0,
                    "Extra Strong": 0.0
                }
            },
            "roomNote": {
                "level": "Very Pleasant",
                "distribution": {
                    "Unnoticeable": 0.0,
                    "Pleasant": 50.0,
                    "Very Pleasant": 100.0,
                    "Pleasant to Tolerable": 0.0,
                    "Tolerable": 0.0,
                    "Tolerable to Strong": 0.0,
                    "Strong": 0.0,
                    "Very Strong": 0.0,
                    "Extra Strong": 0.0,
                    "Overwhelming": 0.0
                }
            },
            "taste": {
                "level": "Medium",
                "distribution": {
                    "Extremely Mild (Flat)": 0.0,
                    "Very Mild": 0.0,
                    "Mild": 0.0,
                    "Mild to Medium": 0.0,
                    "Medium": 100.0,
                    "Medium to Full": 50.0,
                    "Full": 0.0,
                    "Very Full": 0.0,
                    "Extra Full": 0.0,
                    "Overwhelming": 0.0
                }
            }
        }
    }
}