{
    "irishblessing": {
        "blender": "Cornell & Diehl",
        "name": "Irish Blessing",
        "blendType": "Aromatic",
        "description": "An all black blend that tastes like Irish Mist right to the botom of the bowl.",
        "contents": "Black Cavendish",
        "cut": "Coarse Cut",
        "packaging": "Bulk",
        "country": "United States",
        "production": "Currently available",
        "imagePath": "../blend_pictures/Cornell & Diehl - Irish Blessing.jpg",
        "averageRating": 2.73,
        "reviewCount": 23,
        "ratings": {
            "strength": {
                "level": "Mild to Medium",
                "distribution": {
                    "Extremely Mild": 40.0,
                    "Very Mild": 20.0,
                    "Mild": 80.0,
                    "Mild to Medium": 100.0,
                    "Medium": 10.0,
                    "Medium to Strong": 10.0,
                    "Strong": 0.0,
                    "Very Strong": 0.0,
                    "Extremely Strong": 0.0,
                    "Overwhelming": 0.0
                }
            },
            "flavoring": {
                "level": "Medium",
                "distribution": {
                    "None Detected": 0.0,
                    "Extremely Mild": 20.0,
                    "Very Mild": 10.0,
                    "Mild": 10.0,
                    "Mild to Medium": 50.0,
                    "Medium": 100.0,
                    "Medium to Strong": 30.0,
                    "Strong": 10.0,
                    "Very Strong": 30.0,
                    "Extra Strong": 0.0
                }
            },
            "roomNote": {
                "level": "Very Pleasant",
                "distribution": {
                    "Unnoticeable": 27.272727272727,
                    "Pleasant": 100.0,
                    "Very Pleasant": 100.0,
                    "Pleasant to Tolerable": 9.0909090909091,
                    "Tolerable": 0.0,
                    "Tolerable to Strong": 0.0,
                    "Strong": 0.0,
                    "Very Strong": 0.0,
                    "Extra Strong": 0.0,
                    "Overwhelming": 0.0
                }
            },
            "taste": {
                "level": "Mild",
                "distribution": {
                    "Extremely Mild (Flat)": 28.571428571429,
                    "Very Mild": 28.571428571429,
                    "Mild": 100.0,
                    "Mild to Medium": 100.0,
                    "Medium": 85.714285714286,
                    "Medium to Full": 14.285714285714,
                    "Full": 14.285714285714,
                    "Very Full": 0.0,
                    "Extra Full": 0.0,
                    "Overwhelming": 0.0
                }
            }
        }
    }
}