{
    "granbystation": {
        "blender": "Cornell & Diehl",
        "name": "Granby Station",
        "blendType": "Aromatic",
        "description": "Like its namesake conduit to the majestic Rocky Mountains, this mixture of black cavendish and red Virginia leaf \u2014 adorned with the subtle spice of perique and topped with the flavors of vanilla and applejack \u2014 makes for an awe-inspiring experience.",
        "contents": "Black Cavendish,  Burley,  Perique,  Virginia",
        "cut": "Ribbon",
        "packaging": "2 ounce tin, bulk",
        "country": "United States",
        "production": "Currently available",
        "imagePath": "../blend_pictures/Cornell & Diehl - Granby Station.jpg",
        "averageRating": 2.73,
        "reviewCount": 9,
        "ratings": {
            "strength": {
                "level": "Mild",
                "distribution": {
                    "Extremely Mild": 0.0,
                    "Very Mild": 0.0,
                    "Mild": 100.0,
                    "Mild to Medium": 80.0,
                    "Medium": 20.0,
                    "Medium to Strong": 20.0,
                    "Strong": 0.0,
                    "Very Strong": 0.0,
                    "Extremely Strong": 0.0,
                    "Overwhelming": 0.0
                }
            },
            "flavoring": {
                "level": "Mild",
                "distribution": {
                    "None Detected": 0.0,
                    "Extremely Mild": 25.0,
                    "Very Mild": 0.0,
                    "Mild": 100.0,
                    "Mild to Medium": 100.0,
                    "Medium": 25.0,
                    "Medium to Strong": 25.0,
                    "Strong": 0.0,
                    "Very Strong": 0.0,
                    "Extra Strong": 0.0
                }
            },
            "roomNote": {
                "level": "Pleasant to Tolerable",
                "distribution": {
                    "Unnoticeable": 0.0,
                    "Pleasant": 75.0,
                    "Very Pleasant": 25.0,
                    "Pleasant to Tolerable": 100.0,
                    "Tolerable": 75.0,
                    "Tolerable to Strong": 0.0,
                    "Strong": 0.0,
                    "Very Strong": 0.0,
                    "Extra Strong": 0.0,
                    "Overwhelming": 0.0
                }
            },
            "taste": {
                "level": "Mild to Medium",
                "distribution": {
                    "Extremely Mild (Flat)": 16.666666666667,
                    "Very Mild": 0.0,
                    "Mild": 0.0,
                    "Mild to Medium": 100.0,
                    "Medium": 50.0,
                    "Medium to Full": 16.666666666667,
                    "Full": 0.0,
                    "Very Full": 0.0,
                    "Extra Full": 0.0,
                    "Overwhelming": 0.0
                }
            }
        }
    }
}