{
    "johnmarr": {
        "blender": "Cornell & Diehl",
        "name": "John Marr",
        "blendType": "Virginia Based",
        "description": "A poetic mixture of bright and red Virginias with a good portion of Turkish leaf, elevated by genial portions of Perique and black Cavendish, and topped with the flavors of bourbon and vanilla, C&D's John Marr is an unparalleled voyage of sweet complexity.",
        "contents": "Black Cavendish,  Burley,  Oriental/Turkish,  Perique,  Virginia",
        "cut": "Ribbon",
        "packaging": "2oz, 8oz Tin, Bulk",
        "country": "United States",
        "production": "Currently available",
        "imagePath": "../blend_pictures/Cornell & Diehl - John Marr.jpg",
        "averageRating": 3.32,
        "reviewCount": 19,
        "ratings": {
            "strength": {
                "level": "Mild to Medium",
                "distribution": {
                    "Extremely Mild": 0.0,
                    "Very Mild": 0.0,
                    "Mild": 8.3333333333333,
                    "Mild to Medium": 100.0,
                    "Medium": 58.333333333333,
                    "Medium to Strong": 16.666666666667,
                    "Strong": 0.0,
                    "Very Strong": 0.0,
                    "Extremely Strong": 0.0,
                    "Overwhelming": 0.0
                }
            },
            "flavoring": {
                "level": "Mild",
                "distribution": {
                    "None Detected": 0.0,
                    "Extremely Mild": 0.0,
                    "Very Mild": 15.384615384615,
                    "Mild": 100.0,
                    "Mild to Medium": 30.769230769231,
                    "Medium": 23.076923076923,
                    "Medium to Strong": 0.0,
                    "Strong": 0.0,
                    "Very Strong": 0.0,
                    "Extra Strong": 0.0
                }
            },
            "roomNote": {
                "level": "Pleasant",
                "distribution": {
                    "Unnoticeable": 12.5,
                    "Pleasant": 100.0,
                    "Very Pleasant": 62.5,
                    "Pleasant to Tolerable": 75.0,
                    "Tolerable": 12.5,
                    "Tolerable to Strong": 12.5,
                    "Strong": 0.0,
                    "Very Strong": 0.0,
                    "Extra Strong": 0.0,
                    "Overwhelming": 0.0
                }
            },
            "taste": {
                "level": "Medium",
                "distribution": {
                    "Extremely Mild (Flat)": 0.0,
                    "Very Mild": 0.0,
                    "Mild": 0.0,
                    "Mild to Medium": 50.0,
                    "Medium": 100.0,
                    "Medium to Full": 33.333333333333,
                    "Full": 0.0,
                    "Very Full": 0.0,
                    "Extra Full": 0.0,
                    "Overwhelming": 0.0
                }
            }
        }
    }
}