{
    "grandcentral": {
        "imagePath": "../blend_pictures/Drew Estate - Grand Central.jpg",
        "name": "Grand Central",
        "blender": "Drew Estate",
        "blendedBy": "Nicholas Mellilo",
        "manufacturedBy": "Scandinavian Tobacco Group",
        "production": "No longer in production",
        "country": "Denmark",
        "blendType": "Aromatic",
        "contents": "Burley,  Virginia",
        "cut": "Ribbon",
        "packaging": "50 grams tin",
        "flavoring": "Apricot,  Fruit / Citrus",
        "description": "Lose yourself in the hustle and bustle with a bowlful of this mellow blend of tobaccos. You can't quite put your finger on it, but that dense aroma of lightly toasted burley and bright Virginias is awakening your senses.",
        "notes": "Notes:2013 IPCPR release.",
        "reviewCount": 11,
        "totalReviews": 13,
        "averageRating": 3.15,
        "maxRating": 4.0,
        "ratingDistribution": {
            "4_star": 5,
            "3_star": 6,
            "2_star": 1,
            "1_star": 1
        },
        "ratings": {
            "strength": {
                "level": "Very Mild",
                "scale": "Extremely Mild -> Overwhelming",
                "distribution": {
                    "Extremely Mild": 0.0,
                    "Very Mild": 100.0,
                    "Mild": 50.0,
                    "Mild to Medium": 75.0,
                    "Medium": 75.0,
                    "Medium to Strong": 25.0,
                    "Strong": 0.0,
                    "Very Strong": 0.0,
                    "Extremely Strong": 0.0,
                    "Overwhelming": 0.0
                }
            },
            "flavoring": {
                "level": "Medium",
                "scale": "None Detected -> Extra Strong",
                "distribution": {
                    "None Detected": 0.0,
                    "Extremely Mild": 0.0,
                    "Very Mild": 60.0,
                    "Mild": 0.0,
                    "Mild to Medium": 20.0,
                    "Medium": 100.0,
                    "Medium to Strong": 20.0,
                    "Strong": 60.0,
                    "Very Strong": 0.0,
                    "Extra Strong": 0.0
                }
            },
            "roomNote": {
                "level": "Very Pleasant",
                "scale": "Unnoticeable -> Overwhelming",
                "distribution": {
                    "Unnoticeable": 0.0,
                    "Pleasant": 66.666666666667,
                    "Very Pleasant": 100.0,
                    "Pleasant to Tolerable": 16.666666666667,
                    "Tolerable": 16.666666666667,
                    "Tolerable to Strong": 0.0,
                    "Strong": 0.0,
                    "Very Strong": 0.0,
                    "Extra Strong": 0.0,
                    "Overwhelming": 16.666666666667
                }
            },
            "taste": {
                "level": "Medium",
                "scale": "Extremely Mild (Flat) -> Overwhelming",
                "distribution": {
                    "Extremely Mild (Flat)": 0.0,
                    "Very Mild": 20.0,
                    "Mild": 0.0,
                    "Mild to Medium": 60.0,
                    "Medium": 100.0,
                    "Medium to Full": 0.0,
                    "Full": 80.0,
                    "Very Full": 0.0,
                    "Extra Full": 0.0,
                    "Overwhelming": 0.0
                }
            }
        }
    }
}