{
    "toastedblackcavendish": {
        "blender": "Drew Estate",
        "name": "Toasted Black Cavendish",
        "blendType": "Cavendish Based",
        "description": "You could smoke this all day long and never be without company as aromatics capture everyone within a wisp of your smoke. A mild and flavorful blend of toasted cavendish with notes of vanilla and fire cured tobaccos.",
        "contents": "Black Cavendish,  Burley,  Virginia",
        "cut": "Ribbon",
        "packaging": "50 grams tin",
        "country": "Denmark",
        "production": "No longer in production",
        "imagePath": "../blend_pictures/Drew Estate - Toasted Black Cavendish.jpg",
        "averageRating": 2.67,
        "reviewCount": 8,
        "ratings": {
            "strength": {
                "level": "Mild",
                "distribution": {
                    "Extremely Mild": 0.0,
                    "Very Mild": 40.0,
                    "Mild": 100.0,
                    "Mild to Medium": 20.0,
                    "Medium": 20.0,
                    "Medium to Strong": 0.0,
                    "Strong": 0.0,
                    "Very Strong": 0.0,
                    "Extremely Strong": 0.0,
                    "Overwhelming": 0.0
                }
            },
            "flavoring": {
                "level": "Medium",
                "distribution": {
                    "None Detected": 0.0,
                    "Extremely Mild": 0.0,
                    "Very Mild": 0.0,
                    "Mild": 66.666666666667,
                    "Mild to Medium": 66.666666666667,
                    "Medium": 100.0,
                    "Medium to Strong": 66.666666666667,
                    "Strong": 0.0,
                    "Very Strong": 0.0,
                    "Extra Strong": 0.0
                }
            },
            "roomNote": {
                "level": "Very Pleasant",
                "distribution": {
                    "Unnoticeable": 0.0,
                    "Pleasant": 60.0,
                    "Very Pleasant": 100.0,
                    "Pleasant to Tolerable": 20.0,
                    "Tolerable": 0.0,
                    "Tolerable to Strong": 0.0,
                    "Strong": 0.0,
                    "Very Strong": 0.0,
                    "Extra Strong": 0.0,
                    "Overwhelming": 0.0
                }
            },
            "taste": {
                "level": "Mild",
                "distribution": {
                    "Extremely Mild (Flat)": 0.0,
                    "Very Mild": 20.0,
                    "Mild": 100.0,
                    "Mild to Medium": 40.0,
                    "Medium": 20.0,
                    "Medium to Full": 0.0,
                    "Full": 0.0,
                    "Very Full": 0.0,
                    "Extra Full": 0.0,
                    "Overwhelming": 0.0
                }
            }
        }
    }
}