{
    "comfortofbath": {
        "blender": "Frederick Tranter",
        "name": "Comfort of Bath",
        "blendType": "Aromatic",
        "description": "In flavour and aroma this strikes a neat balance between traditional Dark Virginias and aromatic tobaccos. Rich and satisfying.",
        "contents": "Virginia",
        "cut": "Broken Flake",
        "packaging": "Bulk",
        "country": "United Kingdom",
        "production": "Currently available",
        "imagePath": "../blend_pictures/Frederick Tranter - Comfort of Bath.jpg",
        "averageRating": 3.43,
        "reviewCount": 7,
        "ratings": {
            "strength": {
                "level": "Medium",
                "distribution": {
                    "Extremely Mild": 0.0,
                    "Very Mild": 0.0,
                    "Mild": 33.333333333333,
                    "Mild to Medium": 100.0,
                    "Medium": 100.0,
                    "Medium to Strong": 0.0,
                    "Strong": 0.0,
                    "Very Strong": 0.0,
                    "Extremely Strong": 0.0,
                    "Overwhelming": 0.0
                }
            },
            "flavoring": {
                "level": "Medium",
                "distribution": {
                    "None Detected": 0.0,
                    "Extremely Mild": 0.0,
                    "Very Mild": 0.0,
                    "Mild": 0.0,
                    "Mild to Medium": 0.0,
                    "Medium": 100.0,
                    "Medium to Strong": 75.0,
                    "Strong": 0.0,
                    "Very Strong": 0.0,
                    "Extra Strong": 0.0
                }
            },
            "roomNote": {
                "level": "Very Pleasant",
                "distribution": {
                    "Unnoticeable": 0.0,
                    "Pleasant": 75.0,
                    "Very Pleasant": 100.0,
                    "Pleasant to Tolerable": 0.0,
                    "Tolerable": 0.0,
                    "Tolerable to Strong": 0.0,
                    "Strong": 0.0,
                    "Very Strong": 0.0,
                    "Extra Strong": 0.0,
                    "Overwhelming": 0.0
                }
            },
            "taste": {
                "level": "Medium",
                "distribution": {
                    "Extremely Mild (Flat)": 0.0,
                    "Very Mild": 0.0,
                    "Mild": 0.0,
                    "Mild to Medium": 33.333333333333,
                    "Medium": 100.0,
                    "Medium to Full": 33.333333333333,
                    "Full": 66.666666666667,
                    "Very Full": 0.0,
                    "Extra Full": 0.0,
                    "Overwhelming": 0.0
                }
            }
        }
    }
}