{
    "virginiagoldenflake": {
        "imagePath": "../blend_pictures/Pfeifen Huber - Virginia Golden Flake.jpg",
        "name": "Virginia Golden Flake",
        "blender": "Pfeifen Huber",
        "blendedBy": "Georg Huber",
        "manufacturedBy": "Kohlhase & Kopp",
        "production": "Currently available",
        "country": "Germany",
        "blendType": "Straight Virginia",
        "contents": "Virginia",
        "cut": "Flake",
        "packaging": "100 grams tin weight",
        "flavoring": "Honey",
        "description": "Georg Huber's personal Virginia specialty: three different Virginia tobaccos pressed and then cut into ribbon-flakes. Finally a little honey-flavour is added. This is an exclusive flake with a gentle aroma.",
        "notes": "Notes:Formerly known as Virginia Honeydew Flake.",
        "reviewCount": 8,
        "totalReviews": 9,
        "averageRating": 3.89,
        "maxRating": 4.0,
        "ratingDistribution": {
            "4_star": 8,
            "3_star": 1,
            "2_star": 0,
            "1_star": 0
        },
        "ratings": {
            "strength": {
                "level": "Mild to Medium",
                "scale": "Extremely Mild -> Overwhelming",
                "distribution": {
                    "Extremely Mild": 0.0,
                    "Very Mild": 0.0,
                    "Mild": 0.0,
                    "Mild to Medium": 100.0,
                    "Medium": 50.0,
                    "Medium to Strong": 0.0,
                    "Strong": 0.0,
                    "Very Strong": 0.0,
                    "Extremely Strong": 0.0,
                    "Overwhelming": 0.0
                }
            },
            "flavoring": {
                "level": "Very Mild",
                "scale": "None Detected -> Extra Strong",
                "distribution": {
                    "None Detected": 0.0,
                    "Extremely Mild": 40.0,
                    "Very Mild": 100.0,
                    "Mild": 20.0,
                    "Mild to Medium": 20.0,
                    "Medium": 0.0,
                    "Medium to Strong": 0.0,
                    "Strong": 0.0,
                    "Very Strong": 0.0,
                    "Extra Strong": 0.0
                }
            },
            "roomNote": {
                "level": "Pleasant",
                "scale": "Unnoticeable -> Overwhelming",
                "distribution": {
                    "Unnoticeable": 0.0,
                    "Pleasant": 100.0,
                    "Very Pleasant": 25.0,
                    "Pleasant to Tolerable": 75.0,
                    "Tolerable": 25.0,
                    "Tolerable to Strong": 0.0,
                    "Strong": 0.0,
                    "Very Strong": 0.0,
                    "Extra Strong": 0.0,
                    "Overwhelming": 0.0
                }
            },
            "taste": {
                "level": "Medium",
                "scale": "Extremely Mild (Flat) -> Overwhelming",
                "distribution": {
                    "Extremely Mild (Flat)": 0.0,
                    "Very Mild": 0.0,
                    "Mild": 0.0,
                    "Mild to Medium": 33.333333333333,
                    "Medium": 100.0,
                    "Medium to Full": 16.666666666667,
                    "Full": 0.0,
                    "Very Full": 0.0,
                    "Extra Full": 0.0,
                    "Overwhelming": 0.0
                }
            }
        }
    }
}