{
    "sailcavendish(sailaromatic)": {
        "blender": "Scandinavian Tobacco Group (STG)",
        "name": "Sail Cavendish (Sail Aromatic)",
        "blendType": "Aromatic",
        "description": "Sail Aromatic combines the mystique of the Orient with bright, clear Virginia leaf. The result is a pleasant blend that never offends nor tires. A few latakia leaves add to the lasting charm of the recipe.",
        "contents": "Burley,  Cavendish,  Latakia,  Oriental/Turkish,  Virginia",
        "cut": "Coarse Cut",
        "packaging": "50 grams pouch, 6 ounce tin",
        "country": "Denmark",
        "production": "Currently available",
        "imagePath": "../blend_pictures/Scandinavian Tobacco Group (STG) - Sail Cavendish (Sail Aromatic).jpg",
        "averageRating": 2.7,
        "reviewCount": 73,
        "ratings": {
            "strength": {
                "level": "Mild to Medium",
                "distribution": {
                    "Extremely Mild": 2.7027027027027,
                    "Very Mild": 10.810810810811,
                    "Mild": 81.081081081081,
                    "Mild to Medium": 100.0,
                    "Medium": 21.621621621622,
                    "Medium to Strong": 2.7027027027027,
                    "Strong": 2.7027027027027,
                    "Very Strong": 0.0,
                    "Extremely Strong": 0.0,
                    "Overwhelming": 0.0
                }
            },
            "flavoring": {
                "level": "Mild",
                "distribution": {
                    "None Detected": 5.4054054054054,
                    "Extremely Mild": 8.1081081081081,
                    "Very Mild": 24.324324324324,
                    "Mild": 100.0,
                    "Mild to Medium": 56.756756756757,
                    "Medium": 24.324324324324,
                    "Medium to Strong": 2.7027027027027,
                    "Strong": 0.0,
                    "Very Strong": 0.0,
                    "Extra Strong": 0.0
                }
            },
            "roomNote": {
                "level": "Pleasant",
                "distribution": {
                    "Unnoticeable": 2.9411764705882,
                    "Pleasant": 100.0,
                    "Very Pleasant": 41.176470588235,
                    "Pleasant to Tolerable": 67.647058823529,
                    "Tolerable": 20.588235294118,
                    "Tolerable to Strong": 0.0,
                    "Strong": 8.8235294117647,
                    "Very Strong": 0.0,
                    "Extra Strong": 0.0,
                    "Overwhelming": 0.0
                }
            },
            "taste": {
                "level": "Mild to Medium",
                "distribution": {
                    "Extremely Mild (Flat)": 7.6923076923077,
                    "Very Mild": 23.076923076923,
                    "Mild": 92.307692307692,
                    "Mild to Medium": 100.0,
                    "Medium": 65.384615384615,
                    "Medium to Full": 23.076923076923,
                    "Full": 0.0,
                    "Very Full": 3.8461538461538,
                    "Extra Full": 0.0,
                    "Overwhelming": 0.0
                }
            }
        }
    }
}