{
    "sailblack": {
        "blender": "Scandinavian Tobacco Group (STG)",
        "name": "Sail Black",
        "blendType": "Aromatic",
        "description": "Sail Black is a blend with dominating dark tobaccos, specially treated with double fermentation and aging, giving a sweet vanilla type aroma.",
        "contents": "Black Cavendish,  Cavendish",
        "cut": "Mixture",
        "packaging": "50 grams pouch",
        "country": "Denmark",
        "production": "No longer in production",
        "imagePath": "../blend_pictures/Scandinavian Tobacco Group (STG) - Sail Black.jpg",
        "averageRating": 2.2,
        "reviewCount": 5,
        "ratings": {
            "strength": {
                "level": "Very Mild",
                "distribution": {
                    "Extremely Mild": 0.0,
                    "Very Mild": 100.0,
                    "Mild": 0.0,
                    "Mild to Medium": 25.0,
                    "Medium": 0.0,
                    "Medium to Strong": 0.0,
                    "Strong": 0.0,
                    "Very Strong": 0.0,
                    "Extremely Strong": 0.0,
                    "Overwhelming": 0.0
                }
            },
            "flavoring": {
                "level": "Medium to Strong",
                "distribution": {
                    "None Detected": 0.0,
                    "Extremely Mild": 0.0,
                    "Very Mild": 0.0,
                    "Mild": 0.0,
                    "Mild to Medium": 0.0,
                    "Medium": 0.0,
                    "Medium to Strong": 100.0,
                    "Strong": 25.0,
                    "Very Strong": 0.0,
                    "Extra Strong": 0.0
                }
            },
            "roomNote": {
                "level": "Pleasant",
                "distribution": {
                    "Unnoticeable": 0.0,
                    "Pleasant": 100.0,
                    "Very Pleasant": 50.0,
                    "Pleasant to Tolerable": 0.0,
                    "Tolerable": 0.0,
                    "Tolerable to Strong": 0.0,
                    "Strong": 100.0,
                    "Very Strong": 0.0,
                    "Extra Strong": 0.0,
                    "Overwhelming": 0.0
                }
            },
            "taste": {
                "level": "Mild to Medium",
                "distribution": {
                    "Extremely Mild (Flat)": 0.0,
                    "Very Mild": 0.0,
                    "Mild": 50.0,
                    "Mild to Medium": 100.0,
                    "Medium": 0.0,
                    "Medium to Full": 50.0,
                    "Full": 50.0,
                    "Very Full": 0.0,
                    "Extra Full": 0.0,
                    "Overwhelming": 0.0
                }
            }
        }
    }
}